xrobo_calibration/__init__.py
xrobo_calibration/arm_calib/__init__.py
xrobo_calibration/arm_calib/calibration.py
xrobo_calibration/camera_calib/__init__.py
xrobo_calibration/camera_calib/calibration.py
xrobo_calibration/camera_calib/camera_calibrator.py
xrobo_calibration/camera_calib/extrinsic.py
xrobo_calibration/camera_calib/file_io.py
xrobo_calibration/camera_calib/intrinsic.py
xrobo_calibration/camera_calib/pattern_detection.py
xrobo_calibration/camera_calib/utils.py
xrobo_calibration/common/__init__.py
xrobo_calibration/common/data_utils.py
xrobo_calibration/common/io_utils.py
xrobo_calibration/mobile_base_calib/__init__.py
xrobo_calibration/mobile_base_calib/calibration.py
xrobo_calibration-0.1.0.dist-info/LICENSE
xrobo_calibration-0.1.0.dist-info/METADATA
xrobo_calibration-0.1.0.dist-info/WHEEL
xrobo_calibration-0.1.0.dist-info/top_level.txt
xrobo_calibration-0.1.0.dist-info/RECORD
