Metadata-Version: 2.1
Name: xrobo_calibration
Version: 0.1.0
Summary: The xrobo_calibration project provides a robust framework for calibrating robotic systems. It supports tools and methodologies for determining transformations between key components, such as cameras, robotic arms, and mobile base using calibration patterns like chessboards or markers. 
Home-page: https://github.com/v-xchen-v/xrobo_calibration
Author: Xi Chen
Author-email: xichen0907@gmail.com
Classifier: Programming Language :: Python :: 3
Classifier: License :: OSI Approved :: MIT License
Classifier: Operating System :: OS Independent
Requires-Python: >=3.8.10
License-File: LICENSE
Requires-Dist: numpy
Requires-Dist: scipy
Requires-Dist: matplotlib
Requires-Dist: opencv-python
Requires-Dist: imutils
Provides-Extra: dev
Requires-Dist: build ; extra == 'dev'
Requires-Dist: twine ; extra == 'dev'
Requires-Dist: pytest ; extra == 'dev'
Requires-Dist: sphinx ; extra == 'dev'
Requires-Dist: sphinx-rtd-theme ; extra == 'dev'
Requires-Dist: sphinx-autodoc-typehints ; extra == 'dev'
Requires-Dist: myst-parser ; extra == 'dev'
